<?xml version="1.0"?>	<PAGINA>		<ZONA boton="21,43,264,238" audio="0702:7.2" nota="ZONA 1">			<BOTON id="2" vinculo="zoom,AN012,5"/>		</ZONA>		<ZONA boton="19,346,267,286" audio="0712:7.12" nota="ZONA 2">			<BOTON id="2" vinculo="zoom,AN013,3"/>		</ZONA>		<ZONA boton="294,62,183,101" nota="ZONA 3">			<BOTON id="1" vinculo="zoom,TB217,2"/>		</ZONA>		<ZONA boton="294,166,182,161" nota="ZONA 4">			<BOTON id="1" vinculo="zoom,TB217,3"/>		</ZONA>		<ZONA boton="296,346,188,278" nota="ZONA 5">			<BOTON id="1" vinculo="zoom,TB217,4"/>		</ZONA>		<ZONA boton="297,327,79,16" vinculo="goto,1,61" nota="ZONA 6"></ZONA>		<ZONA boton="294,631,82,17" vinculo="goto,1,65" nota="ZONA 7"></ZONA>		<ZONA boton="img,7,61,376,327" vinculo="goto,1,61" nota="ZONA 8"></ZONA>		<ZONA boton="img,7,65,376,634" vinculo="goto,1,65" nota="ZONA 9"></ZONA>	</PAGINA>